django_object_manager/__init__.py
django_object_manager/field_converters.py
django_object_manager/object_manager.py
tests/app/__init__.py
tests/app/apps.py
tests/app/models.py
tests/app/tests.py
tests/functional/__init__.py
tests/functional/test_object_manager.py
django_object_manager-0.0.9.dist-info/LICENSE
django_object_manager-0.0.9.dist-info/METADATA
django_object_manager-0.0.9.dist-info/WHEEL
django_object_manager-0.0.9.dist-info/top_level.txt
django_object_manager-0.0.9.dist-info/RECORD
